steamroll/__init__.py
steamroll/py.typed
steamroll/steamroll.py
steamroll/xyz2mol.py
steamroll-0.0.1.dist-info/METADATA
steamroll-0.0.1.dist-info/WHEEL
steamroll-0.0.1.dist-info/licenses/LICENSE
steamroll-0.0.1.dist-info/RECORD
