Metadata-Version: 2.4
Name: steamroll
Version: 0.0.1
Summary: Package to convert 3D molecules to RDKit
Author: Jonathon Vandezande, Corin Wagen
License: MIT License
License-File: LICENSE
Requires-Python: >=3.11
Requires-Dist: networkx
Requires-Dist: numpy
Requires-Dist: rdkit
